Carousel-0.3.2.data/scripts/carousel-quickstart.py
Carousel-0.3.2.dist-info/DESCRIPTION.rst
Carousel-0.3.2.dist-info/METADATA
Carousel-0.3.2.dist-info/RECORD
Carousel-0.3.2.dist-info/WHEEL
Carousel-0.3.2.dist-info/metadata.json
Carousel-0.3.2.dist-info/top_level.txt
carousel/__init__.py
carousel/version.py
carousel/contrib/__init__.py
carousel/contrib/readers.py
carousel/core/__init__.py
carousel/core/calculations.py
carousel/core/calculators.py
carousel/core/data_readers.py
carousel/core/data_sources.py
carousel/core/exceptions.py
carousel/core/formulas.py
carousel/core/layers.py
carousel/core/models.py
carousel/core/outputs.py
carousel/core/simulations.py
carousel/docs/Makefile
carousel/docs/conf.py
carousel/docs/getting_started.rst
carousel/docs/index.rst
carousel/docs/make.bat
