Metadata-Version: 2.0
Name: Carousel
Version: 0.3.2
Summary: Model Simulation Framework
Home-page: https://github.com/SunPower/Carousel
Author: Mark Mikofski
Author-email: mark.mikofski@sunpowercorp.com
License: BSD 3-clause
Platform: UNKNOWN
Requires: numpy
Requires: xlrd
Requires: scipy
Requires: python_dateutil
Requires: numexpr
Requires: pint (==0.7.2)
Requires: UncertaintyWrapper (>=0.4.1)
Requires: sphinx
Requires: nose
Requires: pandas
Requires: pytz
Requires: pvlib (>=0.4.2)
Requires: dulwich
Requires-Dist: UncertaintyWrapper (>=0.4.1)
Requires-Dist: dulwich
Requires-Dist: nose
Requires-Dist: numexpr
Requires-Dist: numpy
Requires-Dist: pandas
Requires-Dist: pint (==0.7.2)
Requires-Dist: pvlib (>=0.4.2)
Requires-Dist: python-dateutil
Requires-Dist: pytz
Requires-Dist: scipy
Requires-Dist: sphinx
Requires-Dist: xlrd
